plantos_mcp/__init__.py
plantos_mcp/server.py
plantos_mcp-1.0.0.dist-info/METADATA
plantos_mcp-1.0.0.dist-info/WHEEL
plantos_mcp-1.0.0.dist-info/entry_points.txt
plantos_mcp-1.0.0.dist-info/licenses/LICENSE
plantos_mcp-1.0.0.dist-info/RECORD
