Metadata-Version: 2.4
Name: plantos-mcp
Version: 1.0.0
Summary: Agricultural intelligence MCP server for Claude Desktop - soil analysis, weather data, crop predictions, and AI-powered farming recommendations
Project-URL: Homepage, https://plantos.co
Project-URL: Documentation, https://github.com/Plantos-Sensor/mcp-server#readme
Project-URL: Repository, https://github.com/Plantos-Sensor/mcp-server
Project-URL: Download, https://plantos.co/mcp/download
Project-URL: Bug Tracker, https://github.com/Plantos-Sensor/mcp-server/issues
Author-email: Plantos <support@plantos.co>
License: MIT
License-File: LICENSE
Keywords: agriculture,ai,claude,crop-prediction,farming,mcp,model-context-protocol,soil-analysis,weather
Classifier: Development Status :: 4 - Beta
Classifier: Intended Audience :: Developers
Classifier: Intended Audience :: Science/Research
Classifier: License :: OSI Approved :: MIT License
Classifier: Programming Language :: Python :: 3
Classifier: Programming Language :: Python :: 3.10
Classifier: Programming Language :: Python :: 3.11
Classifier: Programming Language :: Python :: 3.12
Classifier: Topic :: Scientific/Engineering :: Artificial Intelligence
Classifier: Topic :: Scientific/Engineering :: Atmospheric Science
Classifier: Topic :: Scientific/Engineering :: GIS
Requires-Python: >=3.10
Requires-Dist: httpx>=0.27.0
Requires-Dist: mcp>=1.0.0
Requires-Dist: pydantic>=2.0.0
Requires-Dist: python-dotenv>=1.0.0
Provides-Extra: dev
Requires-Dist: pytest-asyncio>=0.21.0; extra == 'dev'
Requires-Dist: pytest>=7.0.0; extra == 'dev'
